CHANGES.rst
LICENSE.GPL
LICENSE.txt
MANIFEST.in
Makefile
README.rst
bootstrap-buildout.py
buildout.cfg
heroku.cfg
screenshot.png
setup.py
collective/__init__.py
collective.project.egg-info/PKG-INFO
collective.project.egg-info/SOURCES.txt
collective.project.egg-info/dependency_links.txt
collective.project.egg-info/entry_points.txt
collective.project.egg-info/namespace_packages.txt
collective.project.egg-info/not-zip-safe
collective.project.egg-info/pbr.json
collective.project.egg-info/requires.txt
collective.project.egg-info/top_level.txt
collective/project/__init__.py
collective/project/client.py
collective/project/common.py
collective/project/config.py
collective/project/configure.zcml
collective/project/iteration.py
collective/project/project.py
collective/project/task.py
collective/project/browser/__init__.py
collective/project/browser/clients_view.pt
collective/project/browser/configure.zcml
collective/project/browser/create_iteration.py
collective/project/browser/project.css
collective/project/browser/projects_view.pt
collective/project/browser/projects_view.py
collective/project/client_templates/edit.pt
collective/project/client_templates/view.pt
collective/project/iteration_templates/view.pt
collective/project/profiles/default/controlpanel.xml
collective/project/profiles/default/factorytool.xml
collective/project/profiles/default/metadata.xml
collective/project/profiles/default/portlets.xml
collective/project/profiles/default/propertiestool.xml
collective/project/profiles/default/types.xml
collective/project/profiles/default/workflows.xml
collective/project/profiles/default/types/Folder.xml
collective/project/profiles/default/types/Plone_Site.xml
collective/project/profiles/default/types/client.xml
collective/project/profiles/default/types/iteration.xml
collective/project/profiles/default/types/project.xml
collective/project/profiles/default/types/task.xml
collective/project/profiles/default/workflows/client_workflow/definition.xml
collective/project/profiles/default/workflows/iteration_workflow/definition.xml
collective/project/profiles/default/workflows/project_workflow/definition.xml
collective/project/project_templates/view.pt
collective/project/task_templates/view.pt
collective/project/tests/__init__.py
collective/project/tests/testSkeleton.py