Metadata-Version: 1.1
Name: collective.project
Version: 2.0.0
Summary: Project Management in Plone with Dexterity Content Types
Home-page: https://github.com/collective/collective.project
Author: Alex Clark
Author-email: aclark@aclark.net
License: ZPL
Keywords: dexterity plone project management
Platform: UNKNOWN
Classifier: Framework :: Plone
Classifier: Framework :: Plone :: 4.3
Classifier: Framework :: Plone :: 5.0
Classifier: Programming Language :: Python
Classifier: Topic :: Software Development :: Libraries :: Python Modules
